Metadata-Version: 2.1
Name: apoli-python-extension
Version: 0.0.1
Summary: A python package that can create Datapacks and Resourcepacks using Apoli powers.
Author: ThatRobin
License-File: LICENSE.txt
